src/__init__.py
src/embedding_training.py
src/setup_and_processing.py
src/text_processing.py
magna_search-1.0.1.dist-info/LICENSE
magna_search-1.0.1.dist-info/METADATA
magna_search-1.0.1.dist-info/WHEEL
magna_search-1.0.1.dist-info/entry_points.txt
magna_search-1.0.1.dist-info/top_level.txt
magna_search-1.0.1.dist-info/RECORD
