Metadata-Version: 2.1
Name: magna-search
Version: 1.0.1
Summary: AI-powered embedding similarity search for documents
Home-page: https://github.com/yousef-rafat/Magna
Author: Yousef Gamaleldin
Author-email: yrafat38@gmail.com
Classifier: Programming Language :: Python :: 3
Classifier: License :: OSI Approved :: MIT License
Classifier: Operating System :: OS Independent
Requires-Python: >=3.6
License-File: LICENSE
Requires-Dist: PyMuPDF
Requires-Dist: requests
Requires-Dist: faiss-cpu
Requires-Dist: sentence_transformers
Requires-Dist: python-docx
